codemutator-0.2.0.dist-info/licenses/LICENSE
mutator/__init__.py
mutator/__version__.py
mutator/agent.py
mutator/cli.py
mutator/context/__init__.py
mutator/context/code_analyzer.py
mutator/context/git_integration.py
mutator/context/indexer.py
mutator/context/manager.py
mutator/context/search.py
mutator/context/suppress_warnings.py
mutator/context/vector_store.py
mutator/core/__init__.py
mutator/core/config.py
mutator/core/history.py
mutator/core/path_utils.py
mutator/core/types.py
mutator/execution/executor.py
mutator/execution/planner.py
mutator/llm/__init__.py
mutator/llm/client.py
mutator/tools/__init__.py
mutator/tools/base.py
mutator/tools/batch_tools.py
mutator/tools/builtin.py
mutator/tools/decorator.py
mutator/tools/manager.py
mutator/tools/mcp_server.py
mutator/tools/registry.py
mutator/tools/schema_generator.py
mutator/tools/categories/__init__.py
mutator/tools/categories/ai_tools.py
mutator/tools/categories/development_tools.py
mutator/tools/categories/file_tools.py
mutator/tools/categories/indentation_fixer.py
mutator/tools/categories/search_tools.py
mutator/tools/categories/system_tools.py
mutator/tools/categories/task_tools.py
mutator/tools/categories/web_tools.py
codemutator-0.2.0.dist-info/METADATA
codemutator-0.2.0.dist-info/WHEEL
codemutator-0.2.0.dist-info/entry_points.txt
codemutator-0.2.0.dist-info/top_level.txt
codemutator-0.2.0.dist-info/RECORD
