Metadata-Version: 2.4
Name: CodeMutator
Version: 0.2.0
Summary: A comprehensive Python framework for building coding agents using GenAI
Author-email: Mutator SDK Team <info@codemutator.com>
License: Apache-2.0
Project-URL: Homepage, https://github.com/code-mutator/mutator
Project-URL: Documentation, https://codemutator.readthedocs.io/
Project-URL: Repository, https://github.com/code-mutator/mutator
Project-URL: Bug Reports, https://github.com/code-mutator/mutator/issues
Keywords: mutator,agent,ai,llm,framework,python,development,automation
Classifier: Development Status :: 4 - Beta
Classifier: Intended Audience :: Developers
Classifier: License :: OSI Approved :: Apache Software License
Classifier: Operating System :: OS Independent
Classifier: Programming Language :: Python :: 3
Classifier: Programming Language :: Python :: 3.8
Classifier: Programming Language :: Python :: 3.9
Classifier: Programming Language :: Python :: 3.10
Classifier: Programming Language :: Python :: 3.11
Classifier: Programming Language :: Python :: 3.12
Classifier: Topic :: Software Development :: Libraries :: Python Modules
Classifier: Topic :: Software Development :: Code Generators
Classifier: Topic :: Scientific/Engineering :: Artificial Intelligence
Requires-Python: >=3.8
License-File: LICENSE
Requires-Dist: litellm>=1.35.0
Requires-Dist: pydantic>=2.5.0
Requires-Dist: pydantic-settings>=2.1.0
Requires-Dist: typing-extensions>=4.8.0
Requires-Dist: langchain<0.2.0,>=0.1.0
Requires-Dist: langchain-core<0.2.0,>=0.1.0
Requires-Dist: langgraph<0.1.0,>=0.0.50
Requires-Dist: langchain-community<0.1.0,>=0.0.20
Requires-Dist: chromadb>=0.4.0
Requires-Dist: sentence-transformers>=2.2.0
Requires-Dist: numpy>=1.24.0
Requires-Dist: tree-sitter>=0.20.0
Requires-Dist: tree-sitter-python>=0.20.0
Requires-Dist: tree-sitter-javascript>=0.20.0
Requires-Dist: tree-sitter-typescript>=0.20.0
Requires-Dist: tree-sitter-go>=0.20.0
Requires-Dist: tree-sitter-rust>=0.20.0
Requires-Dist: tree-sitter-java>=0.20.0
Requires-Dist: tree-sitter-cpp>=0.20.0
Requires-Dist: rich>=13.6.0
Requires-Dist: typer>=0.9.0
Requires-Dist: click>=8.1.0
Requires-Dist: prompt-toolkit>=3.0.0
Requires-Dist: httpx>=0.25.0
Requires-Dist: aiohttp>=3.8.0
Requires-Dist: asyncio-mqtt>=0.11.0
Requires-Dist: nest-asyncio>=1.5.0
Requires-Dist: GitPython>=3.1.0
Requires-Dist: watchdog>=3.0.0
Requires-Dist: pathspec>=0.11.0
Requires-Dist: chardet>=5.2.0
Requires-Dist: orjson>=3.9.0
Requires-Dist: jsonschema>=4.19.0
Requires-Dist: python-dotenv>=1.0.0
Requires-Dist: toml>=0.10.2
Requires-Dist: PyYAML>=6.0
Requires-Dist: psutil>=5.9.0
Requires-Dist: mcp>=0.1.0
Requires-Dist: cryptography>=41.0.0
Requires-Dist: validators>=0.22.0
Requires-Dist: pygments>=2.16.0
Requires-Dist: jinja2>=3.1.0
Requires-Dist: requests>=2.31.0
Requires-Dist: beautifulsoup4>=4.12.0
Requires-Dist: duckduckgo-search>=3.8.0
Provides-Extra: dev
Requires-Dist: pytest>=7.4.0; extra == "dev"
Requires-Dist: pytest-asyncio>=0.21.0; extra == "dev"
Requires-Dist: pytest-cov>=4.1.0; extra == "dev"
Requires-Dist: black>=23.7.0; extra == "dev"
Requires-Dist: isort>=5.12.0; extra == "dev"
Requires-Dist: flake8>=6.0.0; extra == "dev"
Requires-Dist: mypy>=1.5.0; extra == "dev"
Requires-Dist: pre-commit>=3.4.0; extra == "dev"
Provides-Extra: docs
Requires-Dist: mkdocs>=1.5.0; extra == "docs"
Requires-Dist: mkdocs-material>=9.2.0; extra == "docs"
Requires-Dist: mkdocstrings>=0.22.0; extra == "docs"
Provides-Extra: all
Requires-Dist: openai>=1.0.0; extra == "all"
Requires-Dist: anthropic>=0.5.0; extra == "all"
Requires-Dist: google-cloud-aiplatform>=1.35.0; extra == "all"
Requires-Dist: azure-ai-ml>=1.10.0; extra == "all"
Dynamic: license-file
